inertia_flask/__init__.py
inertia_flask/cli.py
inertia_flask/extension.py
inertia_flask/helpers.py
inertia_flask/prop_classes.py
inertia_flask/responses.py
inertia_flask/settings.py
inertia_flask/utils.py
inertia_flask/version.py
inertia_flask-1.1.2.dist-info/METADATA
inertia_flask-1.1.2.dist-info/WHEEL
inertia_flask-1.1.2.dist-info/licenses/LICENSE.md
inertia_flask-1.1.2.dist-info/RECORD
