Metadata-Version: 2.4
Name: inertia-flask
Version: 1.1.2
Summary: Inertia Flask is a Flask extension that provides a simple way to build single-page applications (SPAs) using Inertia.js.
Author-email: Coulton Fraser <cjrfraser@gmail.com>
License-File: LICENSE.md
Requires-Python: >=3.10
